mate_rest_client/__init__.py
mate_rest_client/analyses.py
mate_rest_client/artifacts.py
mate_rest_client/builds.py
mate_rest_client/common.py
mate_rest_client/compilations.py
mate_rest_client/graphs.py
mate_rest_client/manticore.py
mate_rest_client/pois.py
mate_rest_client-0.0.1.dist-info/METADATA
mate_rest_client-0.0.1.dist-info/WHEEL
mate_rest_client-0.0.1.dist-info/top_level.txt
mate_rest_client-0.0.1.dist-info/RECORD
