Metadata-Version: 2.1
Name: mate-rest-client
Version: 0.0.1
Summary: A client for MATE's REST API
Author: The MATE authors
Author-email: mate@galois.com
License: BSD-3-Clause
Project-URL: Documentation, https://mate.galois.com
Platform: any
Requires-Python: >=3.8
Requires-Dist: pydantic (~=1.9.0)
Requires-Dist: requests (~=2.27)
Requires-Dist: urllib3 (~=1.26)
Requires-Dist: mate-common
